{
    "web":{
        "client_id":"1047042295114-ik3qr4kt6i9aqteuhkqvajcg2kksvnlq.apps.googleusercontent.com",
        "project_id":"peerless-haiku-291412",
        "auth_uri":"https://accounts.google.com/o/oauth2/auth",
        "token_uri":"https://oauth2.googleapis.com/token",
        "auth_provider_x509_cert_url":"https://www.googleapis.com/oauth2/v1/certs",
        "client_secret":"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",
        "redirect_uris":["https://developers.google.com/oauthplayground"]
        }
    }